LICENSE
README.md
text_imp-0.2.0.1.dist-info/METADATA
text_imp-0.2.0.1.dist-info/WHEEL
text_imp-0.2.0.1.dist-info/licenses/LICENSE
text_imp/__init__.py
text_imp/attachments.py
text_imp/contacts.py
text_imp/text_imp.cpython-312-darwin.so
text_imp-0.2.0.1.dist-info/RECORD
