Metadata-Version: 2.4
Name: text_imp
Version: 0.2.0.1
Requires-Dist: polars>=0.20.0
Requires-Dist: pyarrow>=14.0.1
Requires-Dist: python-dotenv>=1.0.0
License-File: LICENSE
Summary: Python bindings for iMessage and Contacts database access
Keywords: imessage,contacts,macos,database
Author-email: Adam Gluck <contact@adamgluck.com>
License: MIT
Requires-Python: >=3.8
Project-URL: Homepage, https://github.com/adamgluck/text_imp
